{
    "listings": [
        {
            "Job title ": "Global Internship - Artificial intelligence and Cyber Security",
            "Company Name": "Mubadala Investment Company",
            "Location": "Global",
            "Professionalism": "",
            "Application Link": "",
            "Description": "The internship program will provide students with practical industry experience by working alongside professionals in the field. This opportunity will allow students to gain hands on experience, network opportunities and professional development.",
            "Requirements": "UAE National university level student, Bachelor degree undergraduate or graduate, CGPA should be 3 and above"
        }
    ]
}